scar_sim/__init__.py
scar_sim/entity.py
scar_sim/graph.py
scar_sim/order.py
scar_sim/queue.py
scar_sim/simulation.py
scar_sim/utils.py
scar_sim-0.0.5.dist-info/licenses/LICENSE
scar_sim-0.0.5.dist-info/METADATA
scar_sim-0.0.5.dist-info/WHEEL
scar_sim-0.0.5.dist-info/top_level.txt
scar_sim-0.0.5.dist-info/RECORD
