Metadata-Version: 2.4
Name: scar_sim
Version: 0.0.5
Summary: A pure python Supply Chain Adaptation and Resilience simulation tool
Author-email: Connor Makowski <conmak@mit.edu>
Project-URL: Homepage, https://github.com/connor-makowski/scar_sim
Project-URL: Bug Tracker, https://github.com/connor-makowski/scar_sim/issues
Project-URL: Documentation, https://connor-makowski.github.io/scar_sim/scar_sim/enforcer.html
Classifier: Programming Language :: Python :: 3
Classifier: License :: OSI Approved :: MIT License
Classifier: Operating System :: OS Independent
Requires-Python: >=3.11
License-File: LICENSE
Requires-Dist: scgraph==2.15.0
Requires-Dist: dill==0.4.0
Dynamic: license-file
